blacksheep/__init__.py
blacksheep/asgi.pyi
blacksheep/baseapp.c
blacksheep/baseapp.cp312-win_amd64.pyd
blacksheep/baseapp.pxd
blacksheep/baseapp.pyi
blacksheep/baseapp.pyx
blacksheep/contents.c
blacksheep/contents.cp312-win_amd64.pyd
blacksheep/contents.pxd
blacksheep/contents.pyi
blacksheep/contents.pyx
blacksheep/cookies.c
blacksheep/cookies.cp312-win_amd64.pyd
blacksheep/cookies.pxd
blacksheep/cookies.pyi
blacksheep/cookies.pyx
blacksheep/exceptions.c
blacksheep/exceptions.cp312-win_amd64.pyd
blacksheep/exceptions.pxd
blacksheep/exceptions.pyi
blacksheep/exceptions.pyx
blacksheep/headers.c
blacksheep/headers.cp312-win_amd64.pyd
blacksheep/headers.pxd
blacksheep/headers.pyi
blacksheep/headers.pyx
blacksheep/messages.c
blacksheep/messages.cp312-win_amd64.pyd
blacksheep/messages.pxd
blacksheep/messages.pyi
blacksheep/messages.pyx
blacksheep/middlewares.py
blacksheep/multipart.py
blacksheep/normalization.py
blacksheep/py.typed
blacksheep/ranges.py
blacksheep/scribe.c
blacksheep/scribe.cp312-win_amd64.pyd
blacksheep/scribe.pxd
blacksheep/scribe.pyi
blacksheep/scribe.pyx
blacksheep/url.c
blacksheep/url.cp312-win_amd64.pyd
blacksheep/url.pxd
blacksheep/url.pyi
blacksheep/url.pyx
blacksheep/client/__init__.py
blacksheep/client/connection.py
blacksheep/client/cookies.py
blacksheep/client/exceptions.py
blacksheep/client/pool.py
blacksheep/client/session.py
blacksheep/common/__init__.py
blacksheep/common/types.py
blacksheep/common/files/__init__.py
blacksheep/common/files/asyncfs.py
blacksheep/common/files/info.py
blacksheep/common/files/pathsutils.py
blacksheep/server/__init__.py
blacksheep/server/application.py
blacksheep/server/asgi.py
blacksheep/server/bindings.py
blacksheep/server/compression.py
blacksheep/server/controllers.py
blacksheep/server/cors.py
blacksheep/server/csrf.py
blacksheep/server/dataprotection.py
blacksheep/server/di.py
blacksheep/server/env.py
blacksheep/server/errors.py
blacksheep/server/normalization.py
blacksheep/server/process.py
blacksheep_shuttle-0.3.4.dist-info/LICENSE
blacksheep_shuttle-0.3.4.dist-info/METADATA
blacksheep_shuttle-0.3.4.dist-info/WHEEL
blacksheep_shuttle-0.3.4.dist-info/top_level.txt
blacksheep_shuttle-0.3.4.dist-info/RECORD
