Metadata-Version: 2.1
Name: blacksheep-shuttle
Version: 0.3.4
Summary: BlackSheep, but with ShuttleAI's customizations.
Author-email: Roberto Prevato <roberto.prevato@gmail.com>
Project-URL: Homepage, https://github.com/Neoteroi/BlackSheep
Project-URL: Bug Tracker, https://github.com/Neoteroi/BlackSheep/issues
Keywords: blacksheep,web framework,asyncio,shuttleai
Classifier: Development Status :: 5 - Production/Stable
Classifier: License :: OSI Approved :: MIT License
Classifier: Programming Language :: Python :: 3.8
Classifier: Programming Language :: Python :: 3.9
Classifier: Programming Language :: Python :: 3.10
Classifier: Programming Language :: Python :: 3.11
Classifier: Programming Language :: Python :: 3.12
Classifier: Environment :: Web Environment
Classifier: Operating System :: OS Independent
Classifier: Framework :: AsyncIO
Requires-Python: >=3.7
License-File: LICENSE
Requires-Dist: httptools >=0.5
Requires-Dist: certifi >=2022.9.24
Requires-Dist: charset-normalizer ~=3.1.0
Requires-Dist: guardpost >=1.0.2
Requires-Dist: rodi ~=2.0.2
Requires-Dist: essentials <2.0,>=1.1.4
Requires-Dist: essentials-openapi <1.1,>=1.0.6
Requires-Dist: python-dateutil ~=2.8.2
Requires-Dist: itsdangerous ~=2.1.2
Provides-Extra: full
Requires-Dist: cryptography <41.1.0,>=38.0.1 ; extra == 'full'
Requires-Dist: PyJWT ~=2.6.0 ; extra == 'full'
Requires-Dist: websockets ~=10.3 ; extra == 'full'
Provides-Extra: jinja
Requires-Dist: Jinja2 ~=3.1.2 ; extra == 'jinja'
